{"date": "08:32 UTC", "mood": "Market is analyzing data...", "verdict": "WATCH", "reason": "Conflicting signals are driving Bitcoin price action. While potential regulatory clarity (Ripple), strong miner conviction (difficulty jump despite slump), and geopolitical safe-haven bids (US-Iran tensions pushing price) offer long-term bullish sentiment, recent short-term performance weakness ('worst first 50-day start') and the inherent volatility from geopolitical events create significant uncertainty. The market is at a critical juncture, testing key resistance levels amidst high external risk factors and corporate strategy debates.", "headlines": ["Ripple's Brad Garlinghouse says CLARITY bill has '90% chance' of passing by April", "Bitcoin difficulty jumps 15% largest increase since 2021, despite price slump", "Bitcoin nears $68,000, gold jumps as US-Iran tensions return", "Bitcoin logs worst first 50-day start to a year on record", "Metaplanet CEO rebuts critics over bitcoin strategy and transparency"], "links": ["https://www.coindesk.com/policy/2026/02/20/ripple-s-brad-garlinghouse-says-clarity-bill-has-90-chance-of-passing-by-april", "https://www.coindesk.com/markets/2026/02/20/bitcoin-difficulty-jumps-15-largest-increase-since-2021-despite-price-slump", "https://www.coindesk.com/markets/2026/02/20/bitcoin-nears-usd68-000-gold-jumps-as-us-iran-tensions-return", "https://www.coindesk.com/markets/2026/02/20/bitcoin-logs-worst-ever-start-to-a-year-through-first-50-days", "https://www.coindesk.com/markets/2026/02/20/metaplanet-ceo-rebuts-critics-over-bitcoin-strategy-and-transparency"]}